icalevents/__init__.py
icalevents/icaldownload.py
icalevents/icalevents.py
icalevents/icalparser.py
icalevents/py.typed
icalevents-0.3.1.dist-info/LICENSE
icalevents-0.3.1.dist-info/METADATA
icalevents-0.3.1.dist-info/WHEEL
icalevents-0.3.1.dist-info/RECORD
