Metadata-Version: 2.3
Name: icalevents
Version: 0.3.1
Summary: Simple Python 3 library to download, parse and query iCal sources.
License: MIT
Author: Martin Eigenmann
Author-email: github@eigenmannmartin.ch
Requires-Python: >=3.9
Classifier: License :: OSI Approved :: MIT License
Classifier: Programming Language :: Python :: 3
Classifier: Programming Language :: Python :: 3.9
Classifier: Programming Language :: Python :: 3.10
Classifier: Programming Language :: Python :: 3.11
Classifier: Programming Language :: Python :: 3.12
Classifier: Programming Language :: Python :: 3.13
Requires-Dist: icalendar (>=5.0.0)
Requires-Dist: python-dateutil (>=2.9,<3.0)
Requires-Dist: pytz (>=2024.2)
Requires-Dist: urllib3 (>=1.26.5)
